Trinity/Data_Handler.py
Trinity/Modules.py
Trinity/Spectrum_GUI.py
Trinity/__init__.py
Trinity/default_data.txt
Trinity/test_data_storage.dat
Trinity/testing.dat
Trinity/used_file_storage.txt
Trinity/Icons/BackgroundIcon.png
Trinity/Icons/DownIcon.png
Trinity/Icons/ExitIcon.png
Trinity/Icons/LogIcon.png
Trinity/Icons/MCIcon.png
Trinity/Icons/MCMCIcon.png
Trinity/Icons/Mirror.png
Trinity/Icons/PeakIcon.png
Trinity/Icons/RefreshIcon.png
Trinity/Icons/RegionSelectionIcon.png
Trinity/Icons/SumIcon.png
Trinity/Icons/TestIcon.png
Trinity/Icons/TrinityLogo.png
Trinity/Icons/UpIcon.png
Trinity/Icons/YScaleIcon.png
Trinity/Icons/ZoomIcon.png
Trinity/Icons/ZoomInIcon.png
Trinity/Icons/ZoomOutIcon.png
Trinity/Icons/__init__.py
Trinity/Icons/botTrinLogo.png
Trinity/Icons/gaussFitIcon.png
Trinity/Icons/probIcon.png
Trinity/Icons/topTrinLogo.png
TrinitySpectrumAnalysis-1.0.2.dist-info/LICENSE.txt
TrinitySpectrumAnalysis-1.0.2.dist-info/METADATA
TrinitySpectrumAnalysis-1.0.2.dist-info/WHEEL
TrinitySpectrumAnalysis-1.0.2.dist-info/top_level.txt
TrinitySpectrumAnalysis-1.0.2.dist-info/RECORD
