Metadata-Version: 2.1
Name: TrinitySpectrumAnalysis
Version: 1.0.2
Summary: UNKNOWN
Home-page: https://github.com/Cademan10/Trinity
Author: Cade Rodgers
Author-email: <cader@live.unc.edu>
License: Creative Commons Attribution-Noncommercial-Share Alike license
Platform: UNKNOWN
Requires-Dist: numpy
Requires-Dist: PyQt5
Requires-Dist: pyqtgraph
Requires-Dist: matplotlib
Requires-Dist: scipy
Requires-Dist: rpy2
